inspectds/__init__.py
inspectds/cli.py
inspectds-0.4.0.dist-info/LICENSE
inspectds-0.4.0.dist-info/METADATA
inspectds-0.4.0.dist-info/WHEEL
inspectds-0.4.0.dist-info/entry_points.txt
inspectds-0.4.0.dist-info/RECORD
