Metadata-Version: 2.1
Name: inspectds
Version: 0.4.0
Summary: 
Home-page: https://github.com/pmav99/inspectds.git
License: Unlicense
Author: Panos Mavrogiorgos
Author-email: pmav99@gmail.com
Requires-Python: >=3.9,<4.0
Classifier: Development Status :: 4 - Beta
Classifier: Environment :: Console
Classifier: Intended Audience :: Developers
Classifier: Intended Audience :: Science/Research
Classifier: License :: OSI Approved
Classifier: License :: OSI Approved :: The Unlicense (Unlicense)
Classifier: Natural Language :: English
Classifier: Operating System :: OS Independent
Classifier: Programming Language :: Python :: 3
Classifier: Programming Language :: Python :: 3.9
Classifier: Programming Language :: Python :: 3.10
Classifier: Programming Language :: Python :: 3.11
Classifier: Programming Language :: Python :: 3.12
Classifier: Topic :: Scientific/Engineering
Classifier: Topic :: Utilities
Provides-Extra: all
Provides-Extra: grib
Provides-Extra: selafin
Requires-Dist: cfgrib (>=0.9) ; extra == "grib" or extra == "all"
Requires-Dist: netcdf4
Requires-Dist: rioxarray
Requires-Dist: typer (>=0.12.0)
Requires-Dist: xarray
Requires-Dist: xarray-selafin ; extra == "selafin" or extra == "all"
Requires-Dist: zarr (>=2.8)
Project-URL: Repository, https://github.com/pmav99/inspectds.git
